{
	"configurations" : 
	[
		{
			"directories" : 
			[
				{
					"build" : ".",
					"jsonFile" : "directory-.-Debug-d0094a50bb2071803777.json",
					"minimumCMakeVersion" : 
					{
						"string" : "2.8"
					},
					"projectIndex" : 0,
					"source" : ".",
					"targetIndexes" : 
					[
						0,
						1,
						2,
						3
					]
				}
			],
			"name" : "Debug",
			"projects" : 
			[
				{
					"directoryIndexes" : 
					[
						0
					],
					"name" : "MazeVisibility",
					"targetIndexes" : 
					[
						0,
						1,
						2,
						3
					]
				}
			],
			"targets" : 
			[
				{
					"directoryIndex" : 0,
					"id" : "ALL_BUILD::@6890427a1f51a3e7e1df",
					"jsonFile" : "target-ALL_BUILD-Debug-d3a8b3e95d67c957a2e9.json",
					"name" : "ALL_BUILD",
					"projectIndex" : 0
				},
				{
					"directoryIndex" : 0,
					"id" : "MazeLib::@6890427a1f51a3e7e1df",
					"jsonFile" : "target-MazeLib-Debug-cc783396150fc5e55398.json",
					"name" : "MazeLib",
					"projectIndex" : 0
				},
				{
					"directoryIndex" : 0,
					"id" : "MazeVisibility::@6890427a1f51a3e7e1df",
					"jsonFile" : "target-MazeVisibility-Debug-dea645ca9b5aafd51292.json",
					"name" : "MazeVisibility",
					"projectIndex" : 0
				},
				{
					"directoryIndex" : 0,
					"id" : "ZERO_CHECK::@6890427a1f51a3e7e1df",
					"jsonFile" : "target-ZERO_CHECK-Debug-57e3deffcac7ff238841.json",
					"name" : "ZERO_CHECK",
					"projectIndex" : 0
				}
			]
		},
		{
			"directories" : 
			[
				{
					"build" : ".",
					"jsonFile" : "directory-.-Release-d0094a50bb2071803777.json",
					"minimumCMakeVersion" : 
					{
						"string" : "2.8"
					},
					"projectIndex" : 0,
					"source" : ".",
					"targetIndexes" : 
					[
						0,
						1,
						2,
						3
					]
				}
			],
			"name" : "Release",
			"projects" : 
			[
				{
					"directoryIndexes" : 
					[
						0
					],
					"name" : "MazeVisibility",
					"targetIndexes" : 
					[
						0,
						1,
						2,
						3
					]
				}
			],
			"targets" : 
			[
				{
					"directoryIndex" : 0,
					"id" : "ALL_BUILD::@6890427a1f51a3e7e1df",
					"jsonFile" : "target-ALL_BUILD-Release-d3a8b3e95d67c957a2e9.json",
					"name" : "ALL_BUILD",
					"projectIndex" : 0
				},
				{
					"directoryIndex" : 0,
					"id" : "MazeLib::@6890427a1f51a3e7e1df",
					"jsonFile" : "target-MazeLib-Release-049e553ed20f07121195.json",
					"name" : "MazeLib",
					"projectIndex" : 0
				},
				{
					"directoryIndex" : 0,
					"id" : "MazeVisibility::@6890427a1f51a3e7e1df",
					"jsonFile" : "target-MazeVisibility-Release-894c29342fb4a4c2254d.json",
					"name" : "MazeVisibility",
					"projectIndex" : 0
				},
				{
					"directoryIndex" : 0,
					"id" : "ZERO_CHECK::@6890427a1f51a3e7e1df",
					"jsonFile" : "target-ZERO_CHECK-Release-57e3deffcac7ff238841.json",
					"name" : "ZERO_CHECK",
					"projectIndex" : 0
				}
			]
		},
		{
			"directories" : 
			[
				{
					"build" : ".",
					"jsonFile" : "directory-.-MinSizeRel-d0094a50bb2071803777.json",
					"minimumCMakeVersion" : 
					{
						"string" : "2.8"
					},
					"projectIndex" : 0,
					"source" : ".",
					"targetIndexes" : 
					[
						0,
						1,
						2,
						3
					]
				}
			],
			"name" : "MinSizeRel",
			"projects" : 
			[
				{
					"directoryIndexes" : 
					[
						0
					],
					"name" : "MazeVisibility",
					"targetIndexes" : 
					[
						0,
						1,
						2,
						3
					]
				}
			],
			"targets" : 
			[
				{
					"directoryIndex" : 0,
					"id" : "ALL_BUILD::@6890427a1f51a3e7e1df",
					"jsonFile" : "target-ALL_BUILD-MinSizeRel-d3a8b3e95d67c957a2e9.json",
					"name" : "ALL_BUILD",
					"projectIndex" : 0
				},
				{
					"directoryIndex" : 0,
					"id" : "MazeLib::@6890427a1f51a3e7e1df",
					"jsonFile" : "target-MazeLib-MinSizeRel-affb613f80f5e41dd135.json",
					"name" : "MazeLib",
					"projectIndex" : 0
				},
				{
					"directoryIndex" : 0,
					"id" : "MazeVisibility::@6890427a1f51a3e7e1df",
					"jsonFile" : "target-MazeVisibility-MinSizeRel-e70be72fcd04c6eec3a0.json",
					"name" : "MazeVisibility",
					"projectIndex" : 0
				},
				{
					"directoryIndex" : 0,
					"id" : "ZERO_CHECK::@6890427a1f51a3e7e1df",
					"jsonFile" : "target-ZERO_CHECK-MinSizeRel-57e3deffcac7ff238841.json",
					"name" : "ZERO_CHECK",
					"projectIndex" : 0
				}
			]
		},
		{
			"directories" : 
			[
				{
					"build" : ".",
					"jsonFile" : "directory-.-RelWithDebInfo-d0094a50bb2071803777.json",
					"minimumCMakeVersion" : 
					{
						"string" : "2.8"
					},
					"projectIndex" : 0,
					"source" : ".",
					"targetIndexes" : 
					[
						0,
						1,
						2,
						3
					]
				}
			],
			"name" : "RelWithDebInfo",
			"projects" : 
			[
				{
					"directoryIndexes" : 
					[
						0
					],
					"name" : "MazeVisibility",
					"targetIndexes" : 
					[
						0,
						1,
						2,
						3
					]
				}
			],
			"targets" : 
			[
				{
					"directoryIndex" : 0,
					"id" : "ALL_BUILD::@6890427a1f51a3e7e1df",
					"jsonFile" : "target-ALL_BUILD-RelWithDebInfo-d3a8b3e95d67c957a2e9.json",
					"name" : "ALL_BUILD",
					"projectIndex" : 0
				},
				{
					"directoryIndex" : 0,
					"id" : "MazeLib::@6890427a1f51a3e7e1df",
					"jsonFile" : "target-MazeLib-RelWithDebInfo-31227f8fad05b5707b5e.json",
					"name" : "MazeLib",
					"projectIndex" : 0
				},
				{
					"directoryIndex" : 0,
					"id" : "MazeVisibility::@6890427a1f51a3e7e1df",
					"jsonFile" : "target-MazeVisibility-RelWithDebInfo-5107eb9d93dd95390a1d.json",
					"name" : "MazeVisibility",
					"projectIndex" : 0
				},
				{
					"directoryIndex" : 0,
					"id" : "ZERO_CHECK::@6890427a1f51a3e7e1df",
					"jsonFile" : "target-ZERO_CHECK-RelWithDebInfo-57e3deffcac7ff238841.json",
					"name" : "ZERO_CHECK",
					"projectIndex" : 0
				}
			]
		}
	],
	"kind" : "codemodel",
	"paths" : 
	{
		"build" : "C:/Computer_Graphic_Project/CG_HW_Project/HW_P2/MazeVisibilityTemplate/MazeVisibility/build",
		"source" : "C:/Computer_Graphic_Project/CG_HW_Project/HW_P2/MazeVisibilityTemplate/MazeVisibility"
	},
	"version" : 
	{
		"major" : 2,
		"minor" : 7
	}
}
